[
  {
    "title": "Process Safety Advisor \u2013 Golden Pass LNG | Sabine Pass / Port Arthur, TX",
    "date": "2025-11-01",
    "location": "Port Arthur, TX",
    "company_hint": "Tarpon Specialty Services"
  },
  {
    "title": "Quality Assurance Engineer IV \u2013 Golden Pass LNG | Sabine Pass / Port Arthur, TX",
    "date": "2025-11-05",
    "location": "Port Arthur, TX",
    "company_hint": "Tarpon Specialty Services"
  },
  {
    "title": "Electrical Planner (SAP) \u2013 Golden Pass LNG | Sabine Pass / Port Arthur, TX",
    "date": "2025-11-06",
    "location": "Port Arthur, TX",
    "company_hint": "Tarpon Specialty Services"
  },
  {
    "title": "********** **********",
    "date": "2025-12-16",
    "location": "****** ****, **",
    "company_hint": "****** **** ***"
  },
  {
    "title": "*********/******** ********* ********",
    "date": "2025-12-13",
    "location": "****** ****, **",
    "company_hint": "****** **** ***"
  },
  {
    "title": "****** ********** ******** *******",
    "date": "2025-12-20",
    "location": "*******, **",
    "company_hint": "****** **** ***"
  },
  {
    "title": "********** ***** **************",
    "date": "2025-12-17",
    "location": "****** ****, **",
    "company_hint": "****** **** ***"
  }
]