[
  {
    "title": "RBM Mechanical Engineer",
    "date": "2025-12-18",
    "location": "Wyoming, MN",
    "company_hint": "Rosenbauer America"
  },
  {
    "title": "Electrical Technician",
    "date": "2025-10-10",
    "location": "Lyons, SD",
    "company_hint": "Rosenbauer America"
  },
  {
    "title": "Electrical Technician",
    "date": "2025-09-26",
    "location": "Lyons, SD",
    "company_hint": "Rosenbauer America"
  },
  {
    "title": "*** ****** (***)",
    "date": "2025-12-18",
    "location": "*****, **",
    "company_hint": "********** *******"
  },
  {
    "title": "*** ***-*** *********",
    "date": "2025-12-02",
    "location": "*******, **",
    "company_hint": "********** *******"
  },
  {
    "title": "*** **** *********",
    "date": "2025-12-02",
    "location": "*******, **",
    "company_hint": "********** *******"
  },
  {
    "title": "*** ********** **********",
    "date": "2025-12-22",
    "location": "*****, **",
    "company_hint": "********** *******"
  }
]